Workbook

Sheet Investor Profile
A1: Bond Portfolio Case Study — Investor Relations Executive, Wint Wealth
A4: Prepared by | B4: Neha Purohit
A5: Prepared for | B5: Wint Wealth - Case Study Submission
A6: Date | B6: 46292
A8: Investor Profile
A9: Available Capital | B9: 10000000
A10: Investment Horizon (months) | B10: 15
A11: Key Objective | B11: Purchase of residential property after 15 months
A12: Target Return (XIRR) | B12: 0.1
A13: Risk Appetite | B13: Conservative - capital safety is priority
A15: Requirements (from case brief)
A16: 1. Safety of Principal — capital loss is not acceptable; funds are earmarked for a house purchase.
A17: 2. Target Return — approx. 10% annualized return (XIRR).
A18: 3. Defined Timeline — strictly a 15-month investment period, with liquidity required at the end.
A20: Approach Summary
A21: • Bonds selected from Wint Wealth’s live bond listings as of 27-Sep-2026.
A22: • All selected bonds are secured instruments with credit ratings of A- or above.
A23: • Coupon rates, YTMs, maturity dates and other bond terms are based on the respective bond listings.
A24: • Bonds are assumed to be held until maturity, with principal repaid at maturity.
A25: • Coupon receipts are recorded on the respective scheduled payment dates.
A26: • Portfolio XIRR is calculated using the actual dated cash flows.

Sheet Bond Selection
A1: Bond Portfolio — Selected from Wint Wealth Live Bonds
A3: ISIN | B3: Issuer | C3: Credit Rating | D3: Coupon (p.a.) | E3: YTM (p.a.) | F3: Tenure (months) | G3: Allocation (₹) | H3: Alloc. (%)
A4: INE1C3207057 | B4: Telangana CF | C4: AA | D4: 0.0935 | E4: 0.08 | F4: 15 | G4: 2531369.3 | H4: =G4/$G$7 -> 0.2531112
A5: INE342T07544 | B5: Navi Finserv | C5: A | D5: 0.1075 | E5: 0.1075 | F5: 15 | G5: 3716518 | H5: =G5/$G$7 -> 0.37161403
A6: INE0RH707013 | B6: Achintya Securities | C6: A- | D6: 0.1 | E6: 0.11 | F6: 15 | G6: 3753129.1 | H6: =G6/$G$7 -> 0.37527477
B7: TOTAL / WEIGHTED AVERAGE | D7: =SUMPRODUCT(D4:D6,G4:G6)/G7 -> 0.10114188 | E7: =SUMPRODUCT(E4:E6,G4:G6)/G7 -> 0.10147763 | F7: =SUMPRODUCT(F4:F6,G4:G6)/G7 -> 15 | G7: =SUM(G4:G6) -> 10001016 | H7: =SUM(H4:H6) -> 1
A9: Note: Actual allocation exceeds the ₹1 crore target by ₹1,016.37 due to whole-unit bond allocation constraints.

Sheet Cash Flow Schedule
A1: Consolidated Monthly Cash Flow Schedule
A2: Assumption: Coupon payments are recorded on each bond’s scheduled payment date, and principal is redeemed at par on the respective maturity date. No reinvestment of interim coupons is assumed.
A5: Cashflow No. | B5: Date | C5: Telangana CF (₹) | D5: Navi Finserv (₹) | E5: Achintya Sec. (₹) | G5: Total Portfolio Cash Flow (₹)
A6: 0 | B6: 46292 | C6: =-'Bond Selection'!G4 -> -2531369.3 | D6: =-'Bond Selection'!G5 -> -3716518 | E6: =-'Bond Selection'!$G$6 -> -3753129.1 | G6: =SUM(C6:E6) -> -10001016
A7: =A6+1 -> 1 | B7: 46308 | C7: 0 | D7: 32515.08 | E7: 0 | G7: =SUM(C7:E7) -> 32515.08
A8: =A7+1 -> 2 | B8: 46321 | C8: 0 | D8: 0 | E8: 34084.95 | G8: =SUM(C8:E8) -> 34084.95
A9: =A8+1 -> 3 | B9: 46339 | C9: 0 | D9: 33598.92 | E9: 0 | G9: =SUM(C9:E9) -> 33598.92
A10: =A9+1 -> 4 | B10: 46352 | C10: 0 | D10: 0 | E10: 32019.74 | G10: =SUM(C10:E10) -> 32019.74
A11: =A10+1 -> 5 | B11: 46369 | C11: 0 | D11: 32515.08 | E11: 0 | G11: =SUM(C11:E11) -> 32515.08
A12: =A11+1 -> 6 | B12: 46382 | C12: 0 | D12: 0 | E12: 30985.25 | G12: =SUM(C12:E12) -> 30985.25
A13: =A12+1 -> 7 | B13: 46387 | C13: 58917.78 | D13: 0 | E13: 0 | G13: =SUM(C13:E13) -> 58917.78
A14: =A13+1 -> 8 | B14: 46400 | C14: 0 | D14: 33598.92 | E14: 0 | G14: =SUM(C14:E14) -> 33598.92
A15: =A14+1 -> 9 | B15: 46413 | C15: 0 | D15: 0 | E15: 32019.74 | G15: =SUM(C15:E15) -> 32019.74
A16: =A15+1 -> 10 | B16: 46431 | C16: 0 | D16: 33598.92 | E16: 0 | G16: =SUM(C16:E16) -> 33598.92
A17: =A16+1 -> 11 | B17: 46444 | C17: 0 | D17: 0 | E17: =32019.74+1256665.41 -> 1288685.1 | G17: =SUM(C17:E17) -> 1288685.1
A18: =A17+1 -> 12 | B18: 46459 | C18: 0 | D18: 30347.41 | E18: 0 | G18: =SUM(C18:E18) -> 30347.41
A19: =A18+1 -> 13 | B19: 46472 | C19: 0 | D19: 0 | E19: 19281.29 | G19: =SUM(C19:E19) -> 19281.29
A20: =A19+1 -> 14 | B20: 46477 | C20: =57636.95+625000 -> 682636.95 | D20: 0 | E20: 0 | G20: =SUM(C20:E20) -> 682636.95
A21: =A20+1 -> 15 | B21: 46490 | C21: 0 | D21: 33598.92 | E21: 0 | G21: =SUM(C21:E21) -> 33598.92
A22: =A21+1 -> 16 | B22: 46503 | C22: 0 | D22: 0 | E22: 21346.49 | G22: =SUM(C22:E22) -> 21346.49
A23: =A22+1 -> 17 | B23: 46520 | C23: 0 | D23: 32515.08 | E23: 0 | G23: =SUM(C23:E23) -> 32515.08
A24: =A23+1 -> 18 | B24: 46533 | C24: 0 | D24: 0 | E24: 20655.45 | G24: =SUM(C24:E24) -> 20655.45
A25: =A24+1 -> 19 | B25: 46551 | C25: 0 | D25: 33598.92 | E25: 0 | G25: =SUM(C25:E25) -> 33598.92
A26: =A25+1 -> 20 | B26: 46564 | C26: 0 | D26: 0 | E26: 21346.49 | G26: =SUM(C26:E26) -> 21346.49
A27: =A26+1 -> 21 | B27: 46568 | C27: =43708.06+625000 -> 668708.06 | D27: 0 | E27: 0 | G27: =SUM(C27:E27) -> 668708.06
A28: =A27+1 -> 22 | B28: 46581 | C28: 0 | D28: 32515.08 | E28: 0 | G28: =SUM(C28:E28) -> 32515.08
A29: =A28+1 -> 23 | B29: 46594 | C29: 0 | D29: 0 | E29: =20655.45+1256665.41 -> 1277320.9 | G29: =SUM(C29:E29) -> 1277320.9
A30: =A29+1 -> 24 | B30: 46612 | C30: 0 | D30: 33598.92 | E30: 0 | G30: =SUM(C30:E30) -> 33598.92
A31: =A30+1 -> 25 | B31: 46625 | C31: 0 | D31: 0 | E31: 10673.25 | G31: =SUM(C31:E31) -> 10673.25
A32: =A31+1 -> 26 | B32: 46643 | C32: 0 | D32: 33598.92 | E32: 0 | G32: =SUM(C32:E32) -> 33598.92
A33: =A32+1 -> 27 | B33: 46656 | C33: 0 | D33: 0 | E33: 10673.25 | G33: =SUM(C33:E33) -> 10673.25
A34: =A33+1 -> 28 | B34: 46660 | C34: =29458.89+625000 -> 654458.89 | D34: 0 | E34: 0 | G34: =SUM(C34:E34) -> 654458.89
A35: =A34+1 -> 29 | B35: 46673 | C35: 0 | D35: 32515.08 | E35: 0 | G35: =SUM(C35:E35) -> 32515.08
A36: =A35+1 -> 30 | B36: 46686 | C36: 0 | D36: 0 | E36: 10329.8 | G36: =SUM(C36:E36) -> 10329.8
A37: =A36+1 -> 31 | B37: 46704 | C37: 0 | D37: 33598.92 | E37: 0 | G37: =SUM(C37:E37) -> 33598.92
A38: =A37+1 -> 32 | B38: 46717 | C38: 0 | D38: 0 | E38: 10673.25 | G38: =SUM(C38:E38) -> 10673.25
A39: =A38+1 -> 33 | B39: 46747 | C39: 0 | D39: 0 | E39: =10329.8+1256669.18 -> 1266999 | G39: =SUM(C39:E39) -> 1266999
A40: =A39+1 -> 34 | B40: 46752 | C40: =14729.45+625000 -> 639729.45 | D40: =52024.12+3680000 -> 3732024.1 | E40: 0 | G40: =SUM(C40:E40) -> 4371753.6
B42: TOTAL CASH IN / (OUT) | G42: =SUM(G6:G40) -> 984266.99
B43: PORTFOLIO XIRR | G43: =XIRR(G6:G40,B6:B40) -> 0.10280469

Sheet Returns Summary
A1: Returns Summary
A3: TOTAL INVESTMENT | D3: PORTFOLIO XIRR
A4: ='Bond Selection'!G7 -> 10001016 | D4: ='Cash Flow Schedule'!G43 -> 0.10280469
A7: Key Metrics
A8: Total Capital Deployed | B8: ='Bond Selection'!G7 -> 10001016
A9: Weighted Average Coupon (p.a.) | B9: ='Bond Selection'!D7 -> 0.10114188
A10: Weighted Average YTM (p.a.) | B10: ='Bond Selection'!E7 -> 0.10147763
A11: Weighted Average Tenure (months) | B11: ='Bond Selection'!F7 -> 15
A12: Total Coupon | B12: ='Cash Flow Schedule'!G42 -> 984266.99
A13: Portfolio XIRR (actual dated cash flows) | B13: ='Cash Flow Schedule'!G43 -> 0.10280469
A14: Target XIRR (case brief) | B14: ='Investor Profile'!B12 -> 0.1
A15: XIRR vs. Target | B15: =B13-B14 -> 0.0028046906
A17: Liquidity Check
A18: Investor's required liquidity date (15 months out) | B18: ='Cash Flow Schedule'!B40 -> 46752
A20: Why this Portfolio Meets the Brief
A21: • Safety: every bond is rated A- or higher (secured Bonds).
A22: • The portfolio comprises 3 secured bonds selected to balance credit quality, diversification and return objectives.
A23: • Portfolio maturity and cash flows are evaluated based on the investor’s 15-month liquidity requirement.
A24: • The portfolio comprises 3 secured bonds selected to balance credit quality, diversification and return objectives.
A25: • Maturity and coupon cash flows are based on the respective bond terms and scheduled payment dates as listed on Wint Wealth.
A27: Note: The final bond in the portfolio matures on 31-Dec-2027 as per its stated bond terms. The maturity date reflects the bond’s contractual maturity and is therefore retained in the cash-flow schedule.
